setup.cfg
setup.py
ec2ssh2/__init__.py
ec2ssh2/__main__.py
ec2ssh2/compat.py
ec2ssh2/config.py
ec2ssh2/ec2_searcher.py
ec2ssh2/env_dict.py
ec2ssh2/exceptions.py
ec2ssh2/util.py
ec2ssh2/version.py
ec2ssh2.egg-info/PKG-INFO
ec2ssh2.egg-info/SOURCES.txt
ec2ssh2.egg-info/dependency_links.txt
ec2ssh2.egg-info/requires.txt
ec2ssh2.egg-info/top_level.txt
ec2ssh2.egg-info/zip-safe